{
  "AAPL": {
    "amount": 0.26,
    "date": "2025-08-11",
    "last_updated": "2025-09-17T08:27:52.175097"
  },
  "IBM": {
    "amount": 1.68,
    "date": "2025-08-08",
    "last_updated": "2025-09-17T08:27:52.781192"
  },
  "XOM": {
    "amount": 0.99,
    "date": "2025-08-15",
    "last_updated": "2025-09-17T08:27:53.549305"
  },
  "OKE": {
    "amount": 1.03,
    "date": "2025-08-01",
    "last_updated": "2025-09-17T08:27:53.921697"
  },
  "BANR": {
    "amount": 0.48,
    "date": "2025-08-05",
    "last_updated": "2025-09-17T08:27:54.307572"
  },
  "F": {
    "amount": 0.15,
    "date": "2025-08-11",
    "last_updated": "2025-09-17T08:27:54.859674"
  },
  "MS": {
    "amount": 1.0,
    "date": "2025-07-31",
    "last_updated": "2025-09-17T08:27:55.181124"
  }
}