{
  "AAPL": {
    "amount": 0.26,
    "date": "2025-05-12",
    "last_updated": "2025-06-14T22:55:53.633646"
  },
  "IBM": {
    "amount": 1.68,
    "date": "2025-05-09",
    "last_updated": "2025-06-14T22:55:54.693374"
  },
  "XOM": {
    "amount": 0.99,
    "date": "2025-05-15",
    "last_updated": "2025-06-14T22:55:55.830639"
  },
  "OKE": {
    "amount": 1.03,
    "date": "2025-05-05",
    "last_updated": "2025-06-14T22:55:56.843275"
  },
  "BANR": {
    "amount": 0.48,
    "date": "2025-04-29",
    "last_updated": "2025-06-14T22:55:57.664726"
  },
  "F": {
    "amount": 0.15,
    "date": "2025-05-12",
    "last_updated": "2025-06-14T22:55:58.919465"
  },
  "MS": {
    "amount": 0.925,
    "date": "2025-04-30",
    "last_updated": "2025-06-14T22:55:59.734127"
  }
}