{
  "AAPL": {
    "amount": 0.26,
    "date": "2025-08-11",
    "last_updated": "2025-11-10T11:09:56.525585"
  },
  "IBM": {
    "amount": 1.68,
    "date": "2025-08-08",
    "last_updated": "2025-11-10T11:09:57.385060"
  },
  "XOM": {
    "amount": 0.99,
    "date": "2025-08-15",
    "last_updated": "2025-11-10T11:09:58.169372"
  },
  "OKE": {
    "amount": 1.03,
    "date": "2025-11-03",
    "last_updated": "2025-11-10T11:09:58.949817"
  },
  "BANR": {
    "amount": 0.5,
    "date": "2025-11-04",
    "last_updated": "2025-11-10T11:09:59.479126"
  },
  "F": {
    "amount": 0.15,
    "date": "2025-11-07",
    "last_updated": "2025-11-10T11:10:00.175530"
  },
  "MS": {
    "amount": 1.0,
    "date": "2025-10-31",
    "last_updated": "2025-11-10T11:10:00.781643"
  }
}