{
  "AAPL": {
    "amount": 0.26,
    "date": "2025-11-10",
    "last_updated": "2025-12-14T23:56:42.047275"
  },
  "IBM": {
    "amount": 1.68,
    "date": "2025-11-10",
    "last_updated": "2025-12-14T23:56:43.167562"
  },
  "XOM": {
    "amount": 1.03,
    "date": "2025-11-14",
    "last_updated": "2025-12-14T23:56:44.148392"
  },
  "OKE": {
    "amount": 1.03,
    "date": "2025-11-03",
    "last_updated": "2025-12-14T23:56:44.898177"
  },
  "BANR": {
    "amount": 0.5,
    "date": "2025-11-04",
    "last_updated": "2025-12-14T23:56:45.379607"
  },
  "F": {
    "amount": 0.15,
    "date": "2025-11-07",
    "last_updated": "2025-12-14T23:56:46.076045"
  },
  "MS": {
    "amount": 1.0,
    "date": "2025-10-31",
    "last_updated": "2025-12-14T23:56:46.634254"
  }
}