{
  "AAPL": {
    "amount": 0.26,
    "date": "2025-05-12",
    "last_updated": "2025-06-20T19:28:30.489371"
  },
  "IBM": {
    "amount": 1.68,
    "date": "2025-05-09",
    "last_updated": "2025-06-20T19:28:31.407645"
  },
  "XOM": {
    "amount": 0.99,
    "date": "2025-05-15",
    "last_updated": "2025-06-20T19:28:32.107015"
  },
  "OKE": {
    "amount": 1.03,
    "date": "2025-05-05",
    "last_updated": "2025-06-20T19:28:32.670589"
  },
  "BANR": {
    "amount": 0.48,
    "date": "2025-04-29",
    "last_updated": "2025-06-20T19:28:33.188988"
  },
  "F": {
    "amount": 0.15,
    "date": "2025-05-12",
    "last_updated": "2025-06-20T19:28:34.395610"
  },
  "MS": {
    "amount": 0.925,
    "date": "2025-04-30",
    "last_updated": "2025-06-20T19:28:35.135580"
  }
}