{
  "AAPL": {
    "amount": 0.25,
    "date": "2025-02-10",
    "last_updated": "2025-05-04T11:50:52.865870"
  },
  "IBM": {
    "amount": 1.67,
    "date": "2025-02-10",
    "last_updated": "2025-05-04T11:50:53.592673"
  },
  "XOM": {
    "amount": 0.99,
    "date": "2025-02-12",
    "last_updated": "2025-05-04T11:50:54.297356"
  },
  "OKE": {
    "amount": 1.03,
    "date": "2025-02-03",
    "last_updated": "2025-05-04T11:50:54.739026"
  },
  "BANR": {
    "amount": 0.48,
    "date": "2025-04-29",
    "last_updated": "2025-05-04T11:50:55.115379"
  },
  "F": {
    "amount": 0.3,
    "date": "2025-02-18",
    "last_updated": "2025-05-04T11:50:55.677509"
  },
  "MS": {
    "amount": 0.925,
    "date": "2025-04-30",
    "last_updated": "2025-05-04T11:50:56.083188"
  }
}