{
  "AAPL": {
    "amount": 0.26,
    "date": "2025-05-12",
    "last_updated": "2025-05-20T05:41:43.213366"
  },
  "IBM": {
    "amount": 1.68,
    "date": "2025-05-09",
    "last_updated": "2025-05-20T05:41:44.290754"
  },
  "XOM": {
    "amount": 0.99,
    "date": "2025-05-15",
    "last_updated": "2025-05-20T05:41:45.186240"
  },
  "OKE": {
    "amount": 1.03,
    "date": "2025-05-05",
    "last_updated": "2025-05-20T05:41:45.654228"
  },
  "BANR": {
    "amount": 0.48,
    "date": "2025-04-29",
    "last_updated": "2025-05-20T05:41:46.324455"
  },
  "F": {
    "amount": 0.15,
    "date": "2025-05-12",
    "last_updated": "2025-05-20T05:41:47.167052"
  },
  "MS": {
    "amount": 0.925,
    "date": "2025-04-30",
    "last_updated": "2025-05-20T05:41:47.798118"
  }
}