{
  "AAPL": {
    "amount": 0.25,
    "date": "2025-02-10",
    "last_updated": "2025-05-12T20:14:56.994473"
  },
  "IBM": {
    "amount": 1.68,
    "date": "2025-05-09",
    "last_updated": "2025-05-12T20:14:57.612213"
  },
  "XOM": {
    "amount": 0.99,
    "date": "2025-02-12",
    "last_updated": "2025-05-12T20:14:58.247990"
  },
  "OKE": {
    "amount": 1.03,
    "date": "2025-05-05",
    "last_updated": "2025-05-12T20:14:58.766470"
  },
  "BANR": {
    "amount": 0.48,
    "date": "2025-04-29",
    "last_updated": "2025-05-12T20:14:59.146523"
  },
  "F": {
    "amount": 0.3,
    "date": "2025-02-18",
    "last_updated": "2025-05-12T20:14:59.655464"
  },
  "MS": {
    "amount": 0.925,
    "date": "2025-04-30",
    "last_updated": "2025-05-12T20:15:00.032618"
  }
}