{
  "AAPL": {
    "amount": 0.25,
    "date": "2025-02-10",
    "last_updated": "2025-04-19T21:59:07.147558"
  },
  "IBM": {
    "amount": 1.67,
    "date": "2025-02-10",
    "last_updated": "2025-04-19T21:59:08.090235"
  },
  "XOM": {
    "amount": 0.99,
    "date": "2025-02-12",
    "last_updated": "2025-04-19T21:59:08.681156"
  },
  "OKE": {
    "amount": 1.03,
    "date": "2025-02-03",
    "last_updated": "2025-04-19T21:59:09.086717"
  },
  "BANR": {
    "amount": 0.48,
    "date": "2025-02-04",
    "last_updated": "2025-04-19T21:59:09.423154"
  },
  "F": {
    "amount": 0.3,
    "date": "2025-02-18",
    "last_updated": "2025-04-19T21:59:10.039282"
  },
  "MS": {
    "amount": 0.925,
    "date": "2025-01-31",
    "last_updated": "2025-04-19T21:59:10.372083"
  }
}