{
  "AAPL": {
    "amount": 0.25,
    "date": "2025-02-10",
    "last_updated": "2025-04-24T19:56:54.134847"
  },
  "IBM": {
    "amount": 1.67,
    "date": "2025-02-10",
    "last_updated": "2025-04-24T19:56:54.986885"
  },
  "XOM": {
    "amount": 0.99,
    "date": "2025-02-12",
    "last_updated": "2025-04-24T19:56:55.626042"
  },
  "OKE": {
    "amount": 1.03,
    "date": "2025-02-03",
    "last_updated": "2025-04-24T19:56:56.130806"
  },
  "BANR": {
    "amount": 0.48,
    "date": "2025-02-04",
    "last_updated": "2025-04-24T19:56:56.482621"
  },
  "F": {
    "amount": 0.3,
    "date": "2025-02-18",
    "last_updated": "2025-04-24T19:56:57.833642"
  },
  "MS": {
    "amount": 0.925,
    "date": "2025-01-31",
    "last_updated": "2025-04-24T19:56:58.193418"
  }
}