{
  "AAPL": {
    "amount": 0.26,
    "date": "2025-05-12",
    "last_updated": "2025-08-10T02:19:30.330462"
  },
  "IBM": {
    "amount": 1.68,
    "date": "2025-08-08",
    "last_updated": "2025-08-10T02:19:31.102218"
  },
  "XOM": {
    "amount": 0.99,
    "date": "2025-05-15",
    "last_updated": "2025-08-10T02:19:31.875655"
  },
  "OKE": {
    "amount": 1.03,
    "date": "2025-08-01",
    "last_updated": "2025-08-10T02:19:32.359691"
  },
  "BANR": {
    "amount": 0.48,
    "date": "2025-08-05",
    "last_updated": "2025-08-10T02:19:32.773135"
  },
  "F": {
    "amount": 0.15,
    "date": "2025-05-12",
    "last_updated": "2025-08-10T02:19:33.321707"
  },
  "MS": {
    "amount": 1.0,
    "date": "2025-07-31",
    "last_updated": "2025-08-10T02:19:33.775533"
  }
}