{
  "AAPL": {
    "amount": 0.26,
    "date": "2025-08-11",
    "last_updated": "2025-09-19T08:25:44.192885"
  },
  "IBM": {
    "amount": 1.68,
    "date": "2025-08-08",
    "last_updated": "2025-09-19T08:25:45.111535"
  },
  "XOM": {
    "amount": 0.99,
    "date": "2025-08-15",
    "last_updated": "2025-09-19T08:25:45.758098"
  },
  "OKE": {
    "amount": 1.03,
    "date": "2025-08-01",
    "last_updated": "2025-09-19T08:25:46.208576"
  },
  "BANR": {
    "amount": 0.48,
    "date": "2025-08-05",
    "last_updated": "2025-09-19T08:25:46.588115"
  },
  "F": {
    "amount": 0.15,
    "date": "2025-08-11",
    "last_updated": "2025-09-19T08:25:47.113491"
  },
  "MS": {
    "amount": 1.0,
    "date": "2025-07-31",
    "last_updated": "2025-09-19T08:25:47.480671"
  }
}