{
  "AAPL": {
    "amount": 0.26,
    "date": "2025-11-10",
    "last_updated": "2025-12-01T08:42:09.071613"
  },
  "IBM": {
    "amount": 1.68,
    "date": "2025-11-10",
    "last_updated": "2025-12-01T08:42:09.800347"
  },
  "XOM": {
    "amount": 1.03,
    "date": "2025-11-14",
    "last_updated": "2025-12-01T08:42:10.736334"
  },
  "OKE": {
    "amount": 1.03,
    "date": "2025-11-03",
    "last_updated": "2025-12-01T08:42:11.223297"
  },
  "BANR": {
    "amount": 0.5,
    "date": "2025-11-04",
    "last_updated": "2025-12-01T08:42:11.772706"
  },
  "F": {
    "amount": 0.15,
    "date": "2025-11-07",
    "last_updated": "2025-12-01T08:42:12.365092"
  },
  "MS": {
    "amount": 1.0,
    "date": "2025-10-31",
    "last_updated": "2025-12-01T08:42:12.833788"
  }
}