{
  "AAPL": {
    "amount": 0.26,
    "date": "2025-05-12",
    "last_updated": "2025-07-23T14:45:17.776224"
  },
  "IBM": {
    "amount": 1.68,
    "date": "2025-05-09",
    "last_updated": "2025-07-23T14:45:18.546549"
  },
  "XOM": {
    "amount": 0.99,
    "date": "2025-05-15",
    "last_updated": "2025-07-23T14:45:19.355156"
  },
  "OKE": {
    "amount": 1.03,
    "date": "2025-05-05",
    "last_updated": "2025-07-23T14:45:19.949850"
  },
  "BANR": {
    "amount": 0.48,
    "date": "2025-04-29",
    "last_updated": "2025-07-23T14:45:20.475173"
  },
  "F": {
    "amount": 0.15,
    "date": "2025-05-12",
    "last_updated": "2025-07-23T14:45:21.191496"
  },
  "MS": {
    "amount": 0.925,
    "date": "2025-04-30",
    "last_updated": "2025-07-23T14:45:21.699509"
  }
}