{
  "AAPL": {
    "amount": 0.26,
    "date": "2025-11-10",
    "last_updated": "2026-01-31T17:48:07.765104"
  },
  "IBM": {
    "amount": 1.68,
    "date": "2025-11-10",
    "last_updated": "2026-01-31T17:48:08.393371"
  },
  "XOM": {
    "amount": 1.03,
    "date": "2025-11-14",
    "last_updated": "2026-01-31T17:48:09.055944"
  },
  "OKE": {
    "amount": 1.03,
    "date": "2025-11-03",
    "last_updated": "2026-01-31T17:48:09.548702"
  },
  "BANR": {
    "amount": 0.5,
    "date": "2025-11-04",
    "last_updated": "2026-01-31T17:48:09.877061"
  },
  "F": {
    "amount": 0.15,
    "date": "2025-11-07",
    "last_updated": "2026-01-31T17:48:10.381301"
  },
  "MS": {
    "amount": 1.0,
    "date": "2026-01-30",
    "last_updated": "2026-01-31T17:48:10.750109"
  }
}