{
  "AAPL": {
    "amount": 0.26,
    "date": "2025-11-10",
    "last_updated": "2025-12-09T21:50:34.400600"
  },
  "IBM": {
    "amount": 1.68,
    "date": "2025-11-10",
    "last_updated": "2025-12-09T21:50:35.120184"
  },
  "XOM": {
    "amount": 1.03,
    "date": "2025-11-14",
    "last_updated": "2025-12-09T21:50:35.785374"
  },
  "OKE": {
    "amount": 1.03,
    "date": "2025-11-03",
    "last_updated": "2025-12-09T21:50:36.222677"
  },
  "BANR": {
    "amount": 0.5,
    "date": "2025-11-04",
    "last_updated": "2025-12-09T21:50:36.963664"
  },
  "F": {
    "amount": 0.15,
    "date": "2025-11-07",
    "last_updated": "2025-12-09T21:50:37.756751"
  },
  "MS": {
    "amount": 1.0,
    "date": "2025-10-31",
    "last_updated": "2025-12-09T21:50:38.143983"
  }
}