{
  "AAPL": {
    "amount": 0.26,
    "date": "2025-05-12",
    "last_updated": "2025-08-11T09:53:33.331229"
  },
  "IBM": {
    "amount": 1.68,
    "date": "2025-08-08",
    "last_updated": "2025-08-11T09:53:34.086602"
  },
  "XOM": {
    "amount": 0.99,
    "date": "2025-05-15",
    "last_updated": "2025-08-11T09:53:34.794314"
  },
  "OKE": {
    "amount": 1.03,
    "date": "2025-08-01",
    "last_updated": "2025-08-11T09:53:35.256690"
  },
  "BANR": {
    "amount": 0.48,
    "date": "2025-08-05",
    "last_updated": "2025-08-11T09:53:35.668570"
  },
  "F": {
    "amount": 0.15,
    "date": "2025-05-12",
    "last_updated": "2025-08-11T09:53:36.262693"
  },
  "MS": {
    "amount": 1.0,
    "date": "2025-07-31",
    "last_updated": "2025-08-11T09:53:36.665536"
  }
}