{
  "AAPL": {
    "amount": 0.26,
    "date": "2025-11-10",
    "last_updated": "2025-12-22T13:54:03.573893"
  },
  "IBM": {
    "amount": 1.68,
    "date": "2025-11-10",
    "last_updated": "2025-12-22T13:54:04.254091"
  },
  "XOM": {
    "amount": 1.03,
    "date": "2025-11-14",
    "last_updated": "2025-12-22T13:54:04.910578"
  },
  "OKE": {
    "amount": 1.03,
    "date": "2025-11-03",
    "last_updated": "2025-12-22T13:54:05.416875"
  },
  "BANR": {
    "amount": 0.5,
    "date": "2025-11-04",
    "last_updated": "2025-12-22T13:54:05.786654"
  },
  "F": {
    "amount": 0.15,
    "date": "2025-11-07",
    "last_updated": "2025-12-22T13:54:06.524026"
  },
  "MS": {
    "amount": 1.0,
    "date": "2025-10-31",
    "last_updated": "2025-12-22T13:54:06.913705"
  }
}