{
  "AAPL": {
    "amount": 0.26,
    "date": "2025-08-11",
    "last_updated": "2025-11-01T11:19:33.467918"
  },
  "IBM": {
    "amount": 1.68,
    "date": "2025-08-08",
    "last_updated": "2025-11-01T11:19:34.360870"
  },
  "XOM": {
    "amount": 0.99,
    "date": "2025-08-15",
    "last_updated": "2025-11-01T11:19:35.196571"
  },
  "OKE": {
    "amount": 1.03,
    "date": "2025-08-01",
    "last_updated": "2025-11-01T11:19:35.664389"
  },
  "BANR": {
    "amount": 0.48,
    "date": "2025-08-05",
    "last_updated": "2025-11-01T11:19:36.187580"
  },
  "F": {
    "amount": 0.15,
    "date": "2025-08-11",
    "last_updated": "2025-11-01T11:19:37.032536"
  },
  "MS": {
    "amount": 1.0,
    "date": "2025-10-31",
    "last_updated": "2025-11-01T11:19:37.586962"
  }
}