{
  "AAPL": {
    "amount": 0.26,
    "date": "2025-08-11",
    "last_updated": "2025-09-07T21:50:17.456017"
  },
  "IBM": {
    "amount": 1.68,
    "date": "2025-08-08",
    "last_updated": "2025-09-07T21:50:18.189194"
  },
  "XOM": {
    "amount": 0.99,
    "date": "2025-08-15",
    "last_updated": "2025-09-07T21:50:18.944679"
  },
  "OKE": {
    "amount": 1.03,
    "date": "2025-08-01",
    "last_updated": "2025-09-07T21:50:19.425515"
  },
  "BANR": {
    "amount": 0.48,
    "date": "2025-08-05",
    "last_updated": "2025-09-07T21:50:19.811409"
  },
  "F": {
    "amount": 0.15,
    "date": "2025-08-11",
    "last_updated": "2025-09-07T21:50:20.455186"
  },
  "MS": {
    "amount": 1.0,
    "date": "2025-07-31",
    "last_updated": "2025-09-07T21:50:20.807574"
  }
}