{
  "AAPL": {
    "amount": 0.26,
    "date": "2025-08-11",
    "last_updated": "2025-08-14T08:37:21.209163"
  },
  "IBM": {
    "amount": 1.68,
    "date": "2025-08-08",
    "last_updated": "2025-08-14T08:37:21.832690"
  },
  "XOM": {
    "amount": 0.99,
    "date": "2025-05-15",
    "last_updated": "2025-08-14T08:37:22.404229"
  },
  "OKE": {
    "amount": 1.03,
    "date": "2025-08-01",
    "last_updated": "2025-08-14T08:37:22.876397"
  },
  "BANR": {
    "amount": 0.48,
    "date": "2025-08-05",
    "last_updated": "2025-08-14T08:37:23.225784"
  },
  "F": {
    "amount": 0.15,
    "date": "2025-08-11",
    "last_updated": "2025-08-14T08:37:23.822651"
  },
  "MS": {
    "amount": 1.0,
    "date": "2025-07-31",
    "last_updated": "2025-08-14T08:37:24.174395"
  }
}