{
  "AAPL": {
    "amount": 0.26,
    "date": "2025-11-10",
    "last_updated": "2025-12-21T23:19:16.673344"
  },
  "IBM": {
    "amount": 1.68,
    "date": "2025-11-10",
    "last_updated": "2025-12-21T23:19:17.442850"
  },
  "XOM": {
    "amount": 1.03,
    "date": "2025-11-14",
    "last_updated": "2025-12-21T23:19:18.420128"
  },
  "OKE": {
    "amount": 1.03,
    "date": "2025-11-03",
    "last_updated": "2025-12-21T23:19:19.371715"
  },
  "BANR": {
    "amount": 0.5,
    "date": "2025-11-04",
    "last_updated": "2025-12-21T23:19:19.765318"
  },
  "F": {
    "amount": 0.15,
    "date": "2025-11-07",
    "last_updated": "2025-12-21T23:19:20.339917"
  },
  "MS": {
    "amount": 1.0,
    "date": "2025-10-31",
    "last_updated": "2025-12-21T23:19:21.062385"
  }
}